pygamma_agreement/__init__.py
pygamma_agreement/alignment.py
pygamma_agreement/cli_apps.py
pygamma_agreement/continuum.py
pygamma_agreement/cst.py
pygamma_agreement/dissimilarity.py
pygamma_agreement/notebook.py
pygamma_agreement/numba_utils.py
pygamma_agreement/sampler.py
pygamma_agreement-0.5.9.dist-info/LICENSE
pygamma_agreement-0.5.9.dist-info/METADATA
pygamma_agreement-0.5.9.dist-info/WHEEL
pygamma_agreement-0.5.9.dist-info/entry_points.txt
pygamma_agreement-0.5.9.dist-info/top_level.txt
pygamma_agreement-0.5.9.dist-info/RECORD
