Metadata-Version: 2.1
Name: pygamma-agreement
Version: 0.5.9
Summary: Inter-annotator agreement measure and alignment written in python
Home-page: https://pygamma-agreement.readthedocs.io/en/latest/
Author: Rachid RIAD
Author-email: Hadrien Titeux <hadrien.titeux@ens.psl.eu>, Rachid Riad <rachid.riad@ens.psl.eu>, Léopold Favre <favreleopold@gmail.com>
Maintainer-email: Hadrien Titeux <hadrien.titeux@ens.psl.eu>
License: MIT
Project-URL: Documentation, https://pygamma-agreement.readthedocs.io/en/latest/
Project-URL: Homepage, https://github.com/bootphon/pygamma-agreement
Project-URL: Repository, https://github.com/bootphon/pygamma-agreement
Classifier: Development Status :: 4 - Beta
Classifier: Intended Audience :: Science/Research
Classifier: License :: OSI Approved :: MIT License
Classifier: Topic :: Scientific/Engineering
Classifier: Topic :: Text Processing :: Linguistic
Classifier: Topic :: Multimedia :: Sound/Audio :: Speech
Classifier: Programming Language :: Python :: 3
Classifier: Programming Language :: Python :: 3.7
Classifier: Programming Language :: Python :: 3.8
Classifier: Programming Language :: Python :: 3.9
Classifier: Programming Language :: Python :: 3.10
Classifier: Programming Language :: Python :: 3.11
Requires-Python: >=3.7
License-File: LICENSE
Requires-Dist: sortedcontainers >=2.0.4
Requires-Dist: numpy >=1.10.4
Requires-Dist: pyannote.core >=4.1
Requires-Dist: cvxpy >=1.0.25
Requires-Dist: cvxopt ==1.3.2
Requires-Dist: tqdm >=4.46.0
Requires-Dist: numba >=0.54.0
Requires-Dist: typing-extensions >=3.7.4.3
Requires-Dist: TextGrid >=1.5
Requires-Dist: pympi-ling >=1.69
Requires-Dist: pyannote.database >=4.1
Requires-Dist: dataclasses >=0.7 ; python_version < "3.7"
Provides-Extra: cbc
Requires-Dist: cylp ; extra == 'cbc'
Provides-Extra: docs
Requires-Dist: sphinx ; extra == 'docs'
Requires-Dist: sphinx-rtd-theme ; extra == 'docs'
Provides-Extra: notebook
Requires-Dist: matplotlib ; extra == 'notebook'
Provides-Extra: testing
Requires-Dist: pytest ; extra == 'testing'
Requires-Dist: cylp ; extra == 'testing'
